apibackuper/__init__.py
apibackuper/__main__.py
apibackuper/auth.py
apibackuper/common.py
apibackuper/constants.py
apibackuper/core.py
apibackuper/rate_limiter.py
apibackuper/cmds/__init__.py
apibackuper/cmds/project.py
apibackuper/schemas/config_schema.json
apibackuper/storage/__init__.py
apibackuper-1.0.12.dist-info/licenses/LICENSE
apibackuper-1.0.12.dist-info/METADATA
apibackuper-1.0.12.dist-info/WHEEL
apibackuper-1.0.12.dist-info/entry_points.txt
apibackuper-1.0.12.dist-info/top_level.txt
apibackuper-1.0.12.dist-info/RECORD
