Metadata-Version: 2.4
Name: apibackuper
Version: 1.0.12
Summary: a command-line tool and python library for API backuping
Home-page: https://github.com/datacoon/apibackuper/
Download-URL: https://github.com/datacoon/apibackuper/
Author: Ivan Begtin
Author-email: Ivan Begtin <ivan@begtin.tech>
License: MIT
Project-URL: Homepage, https://github.com/datacoon/apibackuper/
Project-URL: Documentation, https://github.com/datacoon/apibackuper/
Project-URL: Repository, https://github.com/datacoon/apibackuper/
Project-URL: Issues, https://github.com/datacoon/apibackuper/issues
Project-URL: Download, https://github.com/datacoon/apibackuper/
Keywords: api,json,jsonl,csv,bson,cli,dataset,backup,archive
Classifier: Development Status :: 5 - Production/Stable
Classifier: Programming Language :: Python
Classifier: Programming Language :: Python :: 3
Classifier: Programming Language :: Python :: 3 :: Only
Classifier: Programming Language :: Python :: 3.6
Classifier: Programming Language :: Python :: 3.7
Classifier: Programming Language :: Python :: 3.8
Classifier: Programming Language :: Python :: 3.9
Classifier: Programming Language :: Python :: 3.10
Classifier: Programming Language :: Python :: 3.11
Classifier: Programming Language :: Python :: 3.12
Classifier: Environment :: Console
Classifier: Intended Audience :: Developers
Classifier: Intended Audience :: System Administrators
Classifier: License :: OSI Approved :: MIT License
Classifier: Topic :: Software Development
Classifier: Topic :: System :: Networking
Classifier: Topic :: Terminals
Classifier: Topic :: Text Processing
Classifier: Topic :: Utilities
Requires-Python: >=3.6
License-File: LICENSE
Requires-Dist: typer>=0.9.0
Requires-Dist: lxml>=4.9.3
Requires-Dist: urllib3>=2.0.6
Requires-Dist: requests>=2.31.0
Requires-Dist: xmltodict>=0.13.0
Requires-Dist: PyYAML>=6.0
Requires-Dist: jsonschema>=4.0.0
Requires-Dist: tqdm>=4.66.0
Provides-Extra: recommended
Requires-Dist: aria2p>=0.11.3; extra == "recommended"
Requires-Dist: pandas>=2.0.0; extra == "recommended"
Requires-Dist: pyarrow>=12.0.0; extra == "recommended"
Provides-Extra: dev
Requires-Dist: pre-commit>=3.6.0; extra == "dev"
Requires-Dist: pytest>=7.4.0; extra == "dev"
Requires-Dist: pytest-cov>=4.1.0; extra == "dev"
Requires-Dist: pytest-mock>=3.12.0; extra == "dev"
Requires-Dist: mock>=5.1.0; extra == "dev"
Requires-Dist: black>=23.12.0; extra == "dev"
Requires-Dist: isort>=5.13.0; extra == "dev"
Requires-Dist: flake8>=7.0.0; extra == "dev"
Requires-Dist: flake8-docstrings>=1.7.0; extra == "dev"
Requires-Dist: flake8-bugbear>=23.12.0; extra == "dev"
Requires-Dist: flake8-comprehensions>=3.14.0; extra == "dev"
Requires-Dist: mypy>=1.8.0; extra == "dev"
Requires-Dist: types-requests>=2.31.0; extra == "dev"
Requires-Dist: types-PyYAML>=6.0.0; extra == "dev"
Requires-Dist: bandit>=1.7.6; extra == "dev"
Requires-Dist: pylint>=3.0.0; extra == "dev"
Dynamic: author
Dynamic: download-url
Dynamic: home-page
Dynamic: license-file
